architectures/__init__.py
architectures/cnn.py
architectures/dnn.py
architectures/transformer.py
pygrad/__init__.py
pygrad/activations.py
pygrad/basics.py
pygrad/constants.py
pygrad/losses.py
pygrad/module.py
pygrad/numba_ops.py
pygrad/optims.py
pygrad/tensor.py
pygradproject-0.0.3.dist-info/LICENSE
pygradproject-0.0.3.dist-info/METADATA
pygradproject-0.0.3.dist-info/WHEEL
pygradproject-0.0.3.dist-info/top_level.txt
pygradproject-0.0.3.dist-info/RECORD
