Metadata-Version: 2.1
Name: pygradproject
Version: 0.0.3
Summary: Lightweight Automatic Differentiation in Python.
Home-page: https://github.com/baubels/pygrad
Author: Danila Kurganov
Author-email: dan.kurg@gmail.com
Project-URL: Documentation, https://baubels.github.io/pygrad/
Project-URL: Source Code, https://github.com/baubels/pygrad
Project-URL: Issue Tracker, https://github.com/baubels/pygrad/issues
Classifier: Programming Language :: Python :: 3
Classifier: License :: OSI Approved :: MIT License
Classifier: Operating System :: OS Independent
Requires-Python: >=3.10
License-File: LICENSE
Requires-Dist: numba>=0.60.0
Requires-Dist: numpy==1.26.0
Requires-Dist: opt_einsum>=3.4.0
Provides-Extra: examples
Requires-Dist: dill; extra == "examples"
Requires-Dist: tqdm; extra == "examples"
Provides-Extra: dev
Requires-Dist: pytest; extra == "dev"
Requires-Dist: sphinx; extra == "dev"
Requires-Dist: torch; extra == "dev"
Requires-Dist: dill; extra == "dev"
Requires-Dist: numpy==1.26.0; extra == "dev"
